{
  "dataFormatVersion": 2,
  "type": "attempt",
  "activity": {
    "activeFile": "page.html",
    "activeHtmlFile": "page.html",
    "openedFiles": ["page.html"],
    "studentSettings": {
      "previewIsLive": true,
      "allowedNewTextFileTypes": [
        "text/html",
        "text/css",
        "application/javascript"
      ],
      "canUploadTextFiles": true,
      "canUploadImageFiles": true,
      "canDownloadFiles": true,
      "canSeeFilesList": true,
      "canSetVisibilityBounds": true,
      "canSetFilesPermissions": true,
      "canSeeOutOfBounds": true,
      "canOpenAndCloseTabs": true,
      "canChangePreviewMode": true,
      "allowedSyntaxCheckers": ["text/html"],
      "isCustomSettings": false
    },
    "filesData": {
      "page.html": {
        "contentIndex": 0,
        "contentType": "text",
        "studentPermissions": {
          "firstVisibleLine": 1,
          "lastVisibleLine": 16,
          "canEdit": true,
          "canRename": true,
          "canDelete": true
        }
      },
      "page2.html": {
        "contentIndex": 1,
        "contentType": "text",
        "studentPermissions": {
          "firstVisibleLine": 1,
          "lastVisibleLine": 18,
          "canEdit": true,
          "canRename": true,
          "canDelete": true
        }
      },
      "style.css": {
        "contentIndex": 2,
        "contentType": "text",
        "studentPermissions": {
          "firstVisibleLine": 1,
          "lastVisibleLine": 4,
          "canEdit": true,
          "canRename": true,
          "canDelete": true
        }
      },
      "style2.css": {
        "contentIndex": 3,
        "contentType": "text",
        "studentPermissions": {
          "firstVisibleLine": 1,
          "lastVisibleLine": 3,
          "canEdit": true,
          "canRename": true,
          "canDelete": true
        }
      },
      "script.js": {
        "contentIndex": 4,
        "contentType": "text",
        "studentPermissions": {
          "firstVisibleLine": 1,
          "lastVisibleLine": 1,
          "canEdit": true,
          "canRename": true,
          "canDelete": true
        }
      }
    }
  },
  "attempt": {
    "activeFile": "page.html",
    "activeHtmlFile": "page.html",
    "filesState": {
      "page.html": {
        "contentIndex": 5,
        "contentType": "text",
        "initialName": "page.html",
        "preview": {
          "content": "<!DOCTYPE html>\n<html lang=\"fr\">\n<head>\n  <meta charset=\"UTF-8\">\n  <meta http-equiv=\"X-UA-Compatible\" content=\"IE=edge\">\n  <meta name=\"viewport\" content=\"width=device-width, initial-scale=1.0\">\n  <link rel=\"stylesheet\" href=\"style.css\">\n  <title>Première page</title>\n</head>\n<body>\n  <h1>Première page</h1>\n  <p>Ceci est la première page.</p>\n  <p>Vous pouvez aller voir la deuxième page <a href=\"page2.html\">ici</a>.</p>\n  <script src=\"script.js\"></script>\n</body>\n</html>",
          "upToDate": true
        }
      },
      "page2.html": {
        "contentIndex": 1,
        "contentType": "text",
        "initialName": "page2.html",
        "preview": {
          "content": "<!DOCTYPE html>\n<html lang=\"fr\">\n<head>\n  <meta charset=\"UTF-8\">\n  <meta http-equiv=\"X-UA-Compatible\" content=\"IE=edge\">\n  <meta name=\"viewport\" content=\"width=device-width, initial-scale=1.0\">\n  <link rel=\"stylesheet\" href=\"style.css\">\n  <link rel=\"stylesheet\" href=\"style2.css\">\n  <title>Deuxième page</title>\n</head>\n<body>\n  <h1>Deuxième page</h1>\n  <p>Ceci est la deuxième page.</p>\n  <p>Vous pouvez retourner sur la première page <a href=\"page.html\">ici</a>.</p>\n  <p>Attention, la <a href=\"page3.html\">page 3</a> n'existe pas.</p>\n  <p>Vous pouvez aussi aller sur <a href=\"https://capytale2.ac-paris.fr/\">Capytale</a>.</p>\n</body>\n</html>",
          "upToDate": true
        }
      },
      "style.css": {
        "contentIndex": 2,
        "contentType": "text",
        "initialName": "style.css",
        "preview": {
          "content": "body {\n  background-color: #f0f0f0;\n  font-family: sans-serif;\n}",
          "upToDate": true
        }
      },
      "style2.css": {
        "contentIndex": 3,
        "contentType": "text",
        "initialName": "style2.css",
        "preview": {
          "content": "h1 {\n  color: #aa2222;\n}",
          "upToDate": true
        }
      },
      "script.js": {
        "contentIndex": 4,
        "contentType": "text",
        "initialName": "script.js",
        "preview": {
          "content": "",
          "upToDate": true
        }
      }
    },
    "openedFiles": ["page.html"],
    "previewIsLive": true
  },
  "content": {
    "text": [
      "<!DOCTYPE html>\n<html lang=\"fr\">\n<head>\n  <meta charset=\"UTF-8\">\n  <meta http-equiv=\"X-UA-Compatible\" content=\"IE=edge\">\n  <meta name=\"viewport\" content=\"width=device-width, initial-scale=1.0\">\n  <link rel=\"stylesheet\" href=\"style.css\">\n  <title>Première page (prof)</title>\n</head>\n<body>\n  <h1>Première page</h1>\n  <p>Ceci est la première page.</p>\n  <p>Vous pouvez aller voir la deuxième page <a href=\"page2.html\">ici</a>.</p>\n  <script src=\"script.js\"></script>\n</body>\n</html>",
      "<!DOCTYPE html>\n<html lang=\"fr\">\n<head>\n  <meta charset=\"UTF-8\">\n  <meta http-equiv=\"X-UA-Compatible\" content=\"IE=edge\">\n  <meta name=\"viewport\" content=\"width=device-width, initial-scale=1.0\">\n  <link rel=\"stylesheet\" href=\"style.css\">\n  <link rel=\"stylesheet\" href=\"style2.css\">\n  <title>Deuxième page</title>\n</head>\n<body>\n  <h1>Deuxième page</h1>\n  <p>Ceci est la deuxième page.</p>\n  <p>Vous pouvez retourner sur la première page <a href=\"page.html\">ici</a>.</p>\n  <p>Attention, la <a href=\"page3.html\">page 3</a> n'existe pas.</p>\n  <p>Vous pouvez aussi aller sur <a href=\"https://capytale2.ac-paris.fr/\">Capytale</a>.</p>\n</body>\n</html>",
      "body {\n  background-color: #f0f0f0;\n  font-family: sans-serif;\n}",
      "h1 {\n  color: #aa2222;\n}",
      "",
      "<!DOCTYPE html>\n<html lang=\"fr\">\n<head>\n  <meta charset=\"UTF-8\">\n  <meta http-equiv=\"X-UA-Compatible\" content=\"IE=edge\">\n  <meta name=\"viewport\" content=\"width=device-width, initial-scale=1.0\">\n  <link rel=\"stylesheet\" href=\"style.css\">\n  <title>Première page (élève)</title>\n</head>\n<body>\n  <h1>Première page</h1>\n  <p>Ceci est la première page.</p>\n  <p>Vous pouvez aller voir la deuxième page <a href=\"page2.html\">ici</a>.</p>\n  <script src=\"script.js\"></script>\n</body>\n</html>"
    ],
    "base64": []
  },
  "metadata": {
    "statement": "{\"root\":{\"children\":[{\"children\":[{\"detail\":0,\"format\":0,\"mode\":\"normal\",\"style\":\"\",\"text\":\"Activité exemple\",\"type\":\"text\",\"version\":1}],\"direction\":\"ltr\",\"format\":\"\",\"indent\":0,\"type\":\"heading\",\"version\":1,\"tag\":\"h1\"},{\"children\":[{\"detail\":0,\"format\":0,\"mode\":\"normal\",\"style\":\"\",\"text\":\"Bienvenue dans l'activité exemple de \",\"type\":\"text\",\"version\":1},{\"detail\":0,\"format\":0,\"mode\":\"normal\",\"style\":\"background-color: #ffffff;color: #d0021b;\",\"text\":\"l'activité Web\",\"type\":\"text\",\"version\":1},{\"detail\":0,\"format\":0,\"mode\":\"normal\",\"style\":\"\",\"text\":\" !\",\"type\":\"text\",\"version\":1}],\"direction\":\"ltr\",\"format\":\"\",\"indent\":0,\"type\":\"paragraph\",\"version\":1},{\"children\":[{\"detail\":0,\"format\":0,\"mode\":\"normal\",\"style\":\"\",\"text\":\"Voici un bloc de \",\"type\":\"text\",\"version\":1},{\"detail\":0,\"format\":1,\"mode\":\"normal\",\"style\":\"background-color: #f5a623;\",\"text\":\"code HTML\",\"type\":\"text\",\"version\":1},{\"detail\":0,\"format\":0,\"mode\":\"normal\",\"style\":\"\",\"text\":\" :\",\"type\":\"text\",\"version\":1}],\"direction\":\"ltr\",\"format\":\"\",\"indent\":0,\"type\":\"paragraph\",\"version\":1},{\"children\":[{\"detail\":0,\"format\":0,\"mode\":\"normal\",\"style\":\"\",\"text\":\"<\",\"type\":\"code-highlight\",\"version\":1,\"highlightType\":\"punctuation\"},{\"detail\":0,\"format\":0,\"mode\":\"normal\",\"style\":\"\",\"text\":\"h1\",\"type\":\"code-highlight\",\"version\":1,\"highlightType\":\"tag\"},{\"detail\":0,\"format\":0,\"mode\":\"normal\",\"style\":\"\",\"text\":\">\",\"type\":\"code-highlight\",\"version\":1,\"highlightType\":\"punctuation\"},{\"detail\":0,\"format\":0,\"mode\":\"normal\",\"style\":\"\",\"text\":\"Titre de la page \",\"type\":\"code-highlight\",\"version\":1},{\"detail\":0,\"format\":0,\"mode\":\"normal\",\"style\":\"\",\"text\":\"</\",\"type\":\"code-highlight\",\"version\":1,\"highlightType\":\"punctuation\"},{\"detail\":0,\"format\":0,\"mode\":\"normal\",\"style\":\"\",\"text\":\"h1\",\"type\":\"code-highlight\",\"version\":1,\"highlightType\":\"tag\"},{\"detail\":0,\"format\":0,\"mode\":\"normal\",\"style\":\"\",\"text\":\">\",\"type\":\"code-highlight\",\"version\":1,\"highlightType\":\"punctuation\"},{\"type\":\"linebreak\",\"version\":1},{\"detail\":0,\"format\":0,\"mode\":\"normal\",\"style\":\"\",\"text\":\"<\",\"type\":\"code-highlight\",\"version\":1,\"highlightType\":\"punctuation\"},{\"detail\":0,\"format\":0,\"mode\":\"normal\",\"style\":\"\",\"text\":\"p\",\"type\":\"code-highlight\",\"version\":1,\"highlightType\":\"tag\"},{\"detail\":0,\"format\":0,\"mode\":\"normal\",\"style\":\"\",\"text\":\">\",\"type\":\"code-highlight\",\"version\":1,\"highlightType\":\"punctuation\"},{\"detail\":0,\"format\":0,\"mode\":\"normal\",\"style\":\"\",\"text\":\"Un paragraphe\",\"type\":\"code-highlight\",\"version\":1},{\"detail\":0,\"format\":0,\"mode\":\"normal\",\"style\":\"\",\"text\":\"</\",\"type\":\"code-highlight\",\"version\":1,\"highlightType\":\"punctuation\"},{\"detail\":0,\"format\":0,\"mode\":\"normal\",\"style\":\"\",\"text\":\"p\",\"type\":\"code-highlight\",\"version\":1,\"highlightType\":\"tag\"},{\"detail\":0,\"format\":0,\"mode\":\"normal\",\"style\":\"\",\"text\":\">\",\"type\":\"code-highlight\",\"version\":1,\"highlightType\":\"punctuation\"}],\"direction\":\"ltr\",\"format\":\"\",\"indent\":0,\"type\":\"code\",\"version\":1,\"language\":\"html\"},{\"children\":[{\"children\":[{\"detail\":0,\"format\":0,\"mode\":\"normal\",\"style\":\"\",\"text\":\"Remarque\",\"type\":\"text\",\"version\":1}],\"direction\":null,\"format\":\"\",\"indent\":0,\"type\":\"collapsible-title\",\"version\":1},{\"children\":[{\"children\":[{\"detail\":0,\"format\":0,\"mode\":\"normal\",\"style\":\"\",\"text\":\"On peut ajouter d'autres \",\"type\":\"text\",\"version\":1},{\"detail\":0,\"format\":2,\"mode\":\"normal\",\"style\":\"\",\"text\":\"blocs de code\",\"type\":\"text\",\"version\":1},{\"detail\":0,\"format\":0,\"mode\":\"normal\",\"style\":\"\",\"text\":\" !\",\"type\":\"text\",\"version\":1}],\"direction\":\"ltr\",\"format\":\"\",\"indent\":0,\"type\":\"paragraph\",\"version\":1}],\"direction\":null,\"format\":\"\",\"indent\":0,\"type\":\"collapsible-content\",\"version\":1}],\"direction\":null,\"format\":\"\",\"indent\":0,\"type\":\"collapsible-container\",\"version\":1,\"open\":true},{\"children\":[{\"detail\":0,\"format\":0,\"mode\":\"normal\",\"style\":\"\",\"text\":\"Voici du \",\"type\":\"text\",\"version\":1},{\"detail\":0,\"format\":1,\"mode\":\"normal\",\"style\":\"background-color: #d17fc4;\",\"text\":\"code CSS\",\"type\":\"text\",\"version\":1},{\"detail\":0,\"format\":0,\"mode\":\"normal\",\"style\":\"\",\"text\":\" :\",\"type\":\"text\",\"version\":1}],\"direction\":\"ltr\",\"format\":\"\",\"indent\":0,\"type\":\"paragraph\",\"version\":1},{\"children\":[{\"detail\":0,\"format\":0,\"mode\":\"normal\",\"style\":\"\",\"text\":\"h1\",\"type\":\"code-highlight\",\"version\":1,\"highlightType\":\"selector\"},{\"detail\":0,\"format\":0,\"mode\":\"normal\",\"style\":\"\",\"text\":\" \",\"type\":\"code-highlight\",\"version\":1},{\"detail\":0,\"format\":0,\"mode\":\"normal\",\"style\":\"\",\"text\":\"{\",\"type\":\"code-highlight\",\"version\":1,\"highlightType\":\"punctuation\"},{\"type\":\"linebreak\",\"version\":1},{\"detail\":0,\"format\":0,\"mode\":\"normal\",\"style\":\"\",\"text\":\"  \",\"type\":\"code-highlight\",\"version\":1},{\"detail\":0,\"format\":0,\"mode\":\"normal\",\"style\":\"\",\"text\":\"font-weight\",\"type\":\"code-highlight\",\"version\":1,\"highlightType\":\"property\"},{\"detail\":0,\"format\":0,\"mode\":\"normal\",\"style\":\"\",\"text\":\":\",\"type\":\"code-highlight\",\"version\":1,\"highlightType\":\"punctuation\"},{\"detail\":0,\"format\":0,\"mode\":\"normal\",\"style\":\"\",\"text\":\" bold\",\"type\":\"code-highlight\",\"version\":1},{\"detail\":0,\"format\":0,\"mode\":\"normal\",\"style\":\"\",\"text\":\";\",\"type\":\"code-highlight\",\"version\":1,\"highlightType\":\"punctuation\"},{\"type\":\"linebreak\",\"version\":1},{\"detail\":0,\"format\":0,\"mode\":\"normal\",\"style\":\"\",\"text\":\"}\",\"type\":\"code-highlight\",\"version\":1,\"highlightType\":\"punctuation\"}],\"direction\":\"ltr\",\"format\":\"\",\"indent\":0,\"type\":\"code\",\"version\":1,\"language\":\"css\"},{\"children\":[{\"detail\":0,\"format\":0,\"mode\":\"normal\",\"style\":\"\",\"text\":\"Et enfin, voici du \",\"type\":\"text\",\"version\":1},{\"detail\":0,\"format\":1,\"mode\":\"normal\",\"style\":\"background-color: #b8e986;\",\"text\":\"code Javascript\",\"type\":\"text\",\"version\":1},{\"detail\":0,\"format\":0,\"mode\":\"normal\",\"style\":\"\",\"text\":\" :\",\"type\":\"text\",\"version\":1}],\"direction\":\"ltr\",\"format\":\"\",\"indent\":0,\"type\":\"paragraph\",\"version\":1},{\"children\":[{\"detail\":0,\"format\":0,\"mode\":\"normal\",\"style\":\"\",\"text\":\"console\",\"type\":\"code-highlight\",\"version\":1},{\"detail\":0,\"format\":0,\"mode\":\"normal\",\"style\":\"\",\"text\":\".\",\"type\":\"code-highlight\",\"version\":1,\"highlightType\":\"punctuation\"},{\"detail\":0,\"format\":0,\"mode\":\"normal\",\"style\":\"\",\"text\":\"log\",\"type\":\"code-highlight\",\"version\":1,\"highlightType\":\"function\"},{\"detail\":0,\"format\":0,\"mode\":\"normal\",\"style\":\"\",\"text\":\"(\",\"type\":\"code-highlight\",\"version\":1,\"highlightType\":\"punctuation\"},{\"detail\":0,\"format\":0,\"mode\":\"normal\",\"style\":\"\",\"text\":\"\\\"Le Javascript fonctionne !\\\"\",\"type\":\"code-highlight\",\"version\":1,\"highlightType\":\"string\"},{\"detail\":0,\"format\":0,\"mode\":\"normal\",\"style\":\"\",\"text\":\")\",\"type\":\"code-highlight\",\"version\":1,\"highlightType\":\"punctuation\"},{\"detail\":0,\"format\":0,\"mode\":\"normal\",\"style\":\"\",\"text\":\";\",\"type\":\"code-highlight\",\"version\":1,\"highlightType\":\"punctuation\"}],\"direction\":\"ltr\",\"format\":\"\",\"indent\":0,\"type\":\"code\",\"version\":1,\"language\":\"javascript\"}],\"direction\":\"ltr\",\"format\":\"\",\"indent\":0,\"type\":\"root\",\"version\":1}}"
  }
}
